speedscope.py
speedscope-1.0.dist-info/METADATA
speedscope-1.0.dist-info/WHEEL
speedscope-1.0.dist-info/top_level.txt
speedscope-1.0.dist-info/RECORD
