Metadata-Version: 2.1
Name: speedscope
Version: 1.0
Summary: A python package for using speedscope.app
Home-page: UNKNOWN
Author: Windel Bouwman
Author-email: windel.bouwman@gmail.com
License: UNKNOWN
Platform: UNKNOWN
